README.md
setup.py
cellpose_planer/__init__.py
cellpose_planer/cellpose.py
cellpose_planer/demo.py
cellpose_planer/render.py
cellpose_planer.egg-info/PKG-INFO
cellpose_planer.egg-info/SOURCES.txt
cellpose_planer.egg-info/dependency_links.txt
cellpose_planer.egg-info/requires.txt
cellpose_planer.egg-info/top_level.txt